ipquery/__init__.py
ipquery/templates/main_page.html
ipquery/templates/base.html
ipquery/templates/user.html
ipquery/templates/unauthorized.html
ipquery-1.0.1.dist-info/entry_points.txt
ipquery-1.0.1.dist-info/DESCRIPTION.rst
ipquery-1.0.1.dist-info/RECORD
ipquery-1.0.1.dist-info/metadata.json
ipquery-1.0.1.dist-info/WHEEL
ipquery-1.0.1.dist-info/METADATA
ipquery-1.0.1.dist-info/top_level.txt
