Metadata-Version: 2.0
Name: ipquery
Version: 1.0.1
Summary: Web application to allow SAML authenticated users to searchmultiple AWS accounts for instances by IP
Home-page: https://github.com/gene1wood/ipquery
Author: Gene Wood
Author-email: gene_wood@cementhorizon.com
License: MPL 2.0
Keywords: aws ec2 saml okta
Platform: UNKNOWN
Classifier: Development Status :: 3 - Alpha
Classifier: Intended Audience :: Developers
Classifier: Topic :: System :: Systems Administration
Classifier: License :: OSI Approved :: Mozilla Public License 2.0 (MPL 2.0)
Classifier: Programming Language :: Python :: 2.7
Requires-Dist: ip2instance (>=1.2.0)
Requires-Dist: PyYAML (>=3.11)
Requires-Dist: Flask (>=0.10.1)
Requires-Dist: Flask-Bootstrap (>=3.3.2.1)
Requires-Dist: Flask-Cache (>=0.13.1)
Requires-Dist: Flask-Login (>=0.2.11)
Requires-Dist: Flask-WTF (>=0.11)
Requires-Dist: pysaml2 (>=2.4.0)
